google_cloud_error_reporting_tcspowerflow-1.4.1-py3.9-nspkg.pth
google/cloud/error_reporting/__init__.py
google/cloud/error_reporting/_gapic.py
google/cloud/error_reporting/_logging.py
google/cloud/error_reporting/client.py
google/cloud/error_reporting/util.py
google/cloud/errorreporting_v1beta1/__init__.py
google/cloud/errorreporting_v1beta1/gapic_metadata.json
google/cloud/errorreporting_v1beta1/py.typed
google/cloud/errorreporting_v1beta1/services/__init__.py
google/cloud/errorreporting_v1beta1/services/error_group_service/__init__.py
google/cloud/errorreporting_v1beta1/services/error_group_service/async_client.py
google/cloud/errorreporting_v1beta1/services/error_group_service/client.py
google/cloud/errorreporting_v1beta1/services/error_group_service/transports/__init__.py
google/cloud/errorreporting_v1beta1/services/error_group_service/transports/base.py
google/cloud/errorreporting_v1beta1/services/error_group_service/transports/grpc.py
google/cloud/errorreporting_v1beta1/services/error_group_service/transports/grpc_asyncio.py
google/cloud/errorreporting_v1beta1/services/error_stats_service/__init__.py
google/cloud/errorreporting_v1beta1/services/error_stats_service/async_client.py
google/cloud/errorreporting_v1beta1/services/error_stats_service/client.py
google/cloud/errorreporting_v1beta1/services/error_stats_service/pagers.py
google/cloud/errorreporting_v1beta1/services/error_stats_service/transports/__init__.py
google/cloud/errorreporting_v1beta1/services/error_stats_service/transports/base.py
google/cloud/errorreporting_v1beta1/services/error_stats_service/transports/grpc.py
google/cloud/errorreporting_v1beta1/services/error_stats_service/transports/grpc_asyncio.py
google/cloud/errorreporting_v1beta1/services/report_errors_service/__init__.py
google/cloud/errorreporting_v1beta1/services/report_errors_service/async_client.py
google/cloud/errorreporting_v1beta1/services/report_errors_service/client.py
google_cloud_error_reporting_tcspowerflow-1.4.1.dist-info/LICENSE
google_cloud_error_reporting_tcspowerflow-1.4.1.dist-info/METADATA
google_cloud_error_reporting_tcspowerflow-1.4.1.dist-info/WHEEL
google_cloud_error_reporting_tcspowerflow-1.4.1.dist-info/namespace_packages.txt
google_cloud_error_reporting_tcspowerflow-1.4.1.dist-info/top_level.txt
google_cloud_error_reporting_tcspowerflow-1.4.1.dist-info/RECORD
