Metadata-Version: 2.1
Name: google-cloud-error-reporting-tcspowerflow
Version: 1.4.1
Summary: Error Reporting API client library
Home-page: https://github.com/googleapis/python-error-reporting
Author: Google LLC
Author-email: googleapis-packages@google.com
License: Apache 2.0
Platform: Posix; MacOS X; Windows
Classifier: Development Status :: 4 - Beta
Classifier: Intended Audience :: Developers
Classifier: License :: OSI Approved :: Apache Software License
Classifier: Programming Language :: Python
Classifier: Programming Language :: Python :: 3
Classifier: Programming Language :: Python :: 3.6
Classifier: Programming Language :: Python :: 3.7
Classifier: Programming Language :: Python :: 3.8
Classifier: Programming Language :: Python :: 3.9
Classifier: Programming Language :: Python :: 3.10
Classifier: Operating System :: OS Independent
Classifier: Topic :: Internet
Requires-Python: >=3.6
License-File: LICENSE
Requires-Dist: google-cloud-logging (<3.0.0dev,>=1.14.0)
Requires-Dist: google-api-core[grpc] (<3.0.0dev,>=1.28.0)
Requires-Dist: proto-plus (>=1.4.0)
